tonos_ts4/BaseContract.py
tonos_ts4/__init__.py
tonos_ts4/abi.py
tonos_ts4/address.py
tonos_ts4/decoder.py
tonos_ts4/dump.py
tonos_ts4/global_functions.py
tonos_ts4/globals.py
tonos_ts4/ts4.py
tonos_ts4/util.py
tonos_ts4/darwin/linker_lib.so
tonos_ts4/linux/linker_lib.so
tonos_ts4/win32/linker_lib.pyd
tonos_ts4-0.4.1.dist-info/LICENSE
tonos_ts4-0.4.1.dist-info/METADATA
tonos_ts4-0.4.1.dist-info/WHEEL
tonos_ts4-0.4.1.dist-info/top_level.txt
tonos_ts4-0.4.1.dist-info/RECORD
