Metadata-Version: 2.1
Name: tonos-ts4
Version: 0.4.1
Summary: TestSuite4 is a framework designed to simplify development and testing of TON Contracts
Home-page: https://github.com/tonlabs/TestSuite4
Author: TON Labs
Author-email: info@tonlabs.io
License: Apache
Keywords: freeton ton tvm blockchain testing tonlabs ts4 testsuite
Platform: UNKNOWN
Classifier: Environment :: Console
Classifier: License :: OSI Approved :: Apache Software License
Classifier: Programming Language :: Python
Classifier: Programming Language :: Python :: 3
Classifier: Topic :: Software Development :: Testing
Requires-Python: >=3.6, <3.10
